<mxfile host="app.diagrams.net" modified="2024-01-01T00:00:00.000Z" agent="5.0" version="21.0.0" etag="draw.io" type="device">
    <diagram name="Provider Flow" id="provider-flow">
        <mxGraphModel dx="1422" dy="794" grid="1" gridSize="10" guides="1" tooltips="1" connect="1" arrows="1" fold="1" page="1" pageScale="1" pageWidth="1169" pageHeight="1654" math="0" shadow="0">
            <root>
                <mxCell id="0" />
                <mxCell id="1" parent="0" />

                <!-- Start -->
                <mxCell id="start" value="START" style="ellipse;whiteSpace=wrap;html=1;fillColor=#d5e8d4;strokeColor=#82b366;fontStyle=1;fontSize=14;" vertex="1" parent="1">
                    <mxGeometry x="525" y="40" width="120" height="60" as="geometry" />
                </mxCell>

                <!-- Provider Signs Up -->
                <mxCell id="signup" value="Provider Signs Up" style="rounded=1;whiteSpace=wrap;html=1;fillColor=#dae8fc;strokeColor=#6c8ebf;fontSize=12;" vertex="1" parent="1">
                    <mxGeometry x="495" y="140" width="180" height="60" as="geometry" />
                </mxCell>

                <!-- Email Verification Sent -->
                <mxCell id="emailSent" value="Email Verification Sent" style="rounded=1;whiteSpace=wrap;html=1;fillColor=#dae8fc;strokeColor=#6c8ebf;fontSize=12;" vertex="1" parent="1">
                    <mxGeometry x="495" y="240" width="180" height="60" as="geometry" />
                </mxCell>

                <!-- Email Verified Decision -->
                <mxCell id="emailVerified" value="Email Verified?" style="rhombus;whiteSpace=wrap;html=1;fillColor=#fff2cc;strokeColor=#d6b656;fontSize=12;fontStyle=1;" vertex="1" parent="1">
                    <mxGeometry x="510" y="340" width="150" height="100" as="geometry" />
                </mxCell>

                <!-- Specify Service Areas -->
                <mxCell id="serviceAreas" value="Specify Service Areas" style="rounded=1;whiteSpace=wrap;html=1;fillColor=#dae8fc;strokeColor=#6c8ebf;fontSize=12;" vertex="1" parent="1">
                    <mxGeometry x="495" y="490" width="180" height="60" as="geometry" />
                </mxCell>

                <!-- Request Route Assignment -->
                <mxCell id="routeRequest" value="Request to be Added to Route(s)" style="rounded=1;whiteSpace=wrap;html=1;fillColor=#dae8fc;strokeColor=#6c8ebf;fontSize=12;" vertex="1" parent="1">
                    <mxGeometry x="495" y="590" width="180" height="60" as="geometry" />
                </mxCell>

                <!-- Admin Approval (External) -->
                <mxCell id="adminApproval" value="Admin Reviews &amp; Approves Route Assignment" style="rounded=1;whiteSpace=wrap;html=1;fillColor=#e1d5e7;strokeColor=#9673a6;fontSize=11;fontStyle=2;" vertex="1" parent="1">
                    <mxGeometry x="495" y="690" width="180" height="60" as="geometry" />
                </mxCell>

                <!-- Route Approved Decision -->
                <mxCell id="routeApproved" value="Route Request Approved?" style="rhombus;whiteSpace=wrap;html=1;fillColor=#fff2cc;strokeColor=#d6b656;fontSize=12;fontStyle=1;" vertex="1" parent="1">
                    <mxGeometry x="510" y="790" width="150" height="100" as="geometry" />
                </mxCell>

                <!-- Register Vehicles and Drivers -->
                <mxCell id="registerAssets" value="Register Vehicles and Drivers on System" style="rounded=1;whiteSpace=wrap;html=1;fillColor=#dae8fc;strokeColor=#6c8ebf;fontSize=12;" vertex="1" parent="1">
                    <mxGeometry x="495" y="940" width="180" height="60" as="geometry" />
                </mxCell>

                <!-- Optional: Assign Driver to Vehicle -->
                <mxCell id="assignDriver" value="Optionally Assign Driver to Vehicle" style="rounded=1;whiteSpace=wrap;html=1;fillColor=#dae8fc;strokeColor=#6c8ebf;fontSize=12;dashed=1;" vertex="1" parent="1">
                    <mxGeometry x="495" y="1040" width="180" height="60" as="geometry" />
                </mxCell>

                <!-- Wait for Booking -->
                <mxCell id="waitBooking" value="Wait for Client Booking Requests" style="rounded=1;whiteSpace=wrap;html=1;fillColor=#f8cecc;strokeColor=#b85450;fontSize=12;" vertex="1" parent="1">
                    <mxGeometry x="495" y="1140" width="180" height="60" as="geometry" />
                </mxCell>

                <!-- Booking Notification -->
                <mxCell id="bookingNotif" value="Receive Booking Request Notification" style="rounded=1;whiteSpace=wrap;html=1;fillColor=#dae8fc;strokeColor=#6c8ebf;fontSize=12;" vertex="1" parent="1">
                    <mxGeometry x="495" y="1240" width="180" height="60" as="geometry" />
                </mxCell>

                <!-- View Pending Bookings -->
                <mxCell id="viewPending" value="View Pending Booking List" style="rounded=1;whiteSpace=wrap;html=1;fillColor=#dae8fc;strokeColor=#6c8ebf;fontSize=12;" vertex="1" parent="1">
                    <mxGeometry x="495" y="1340" width="180" height="60" as="geometry" />
                </mxCell>

                <!-- Create Offer -->
                <mxCell id="createOffer" value="Create Offer&#xa;(Vehicle, Price, Validity, Discount, Availability)" style="rounded=1;whiteSpace=wrap;html=1;fillColor=#dae8fc;strokeColor=#6c8ebf;fontSize=12;" vertex="1" parent="1">
                    <mxGeometry x="475" y="1440" width="220" height="70" as="geometry" />
                </mxCell>

                <!-- Check Offer Count -->
                <mxCell id="offerCount" value="Offers for this Booking &lt; 3?" style="rhombus;whiteSpace=wrap;html=1;fillColor=#fff2cc;strokeColor=#d6b656;fontSize=12;fontStyle=1;" vertex="1" parent="1">
                    <mxGeometry x="510" y="1550" width="150" height="100" as="geometry" />
                </mxCell>

                <!-- Submit Offer -->
                <mxCell id="submitOffer" value="Submit Offer to Client" style="rounded=1;whiteSpace=wrap;html=1;fillColor=#dae8fc;strokeColor=#6c8ebf;fontSize=12;" vertex="1" parent="1">
                    <mxGeometry x="495" y="1700" width="180" height="60" as="geometry" />
                </mxCell>

                <!-- Wait for Client Response -->
                <mxCell id="waitResponse" value="Wait for Client's Decision" style="rounded=1;whiteSpace=wrap;html=1;fillColor=#f8cecc;strokeColor=#b85450;fontSize=12;" vertex="1" parent="1">
                    <mxGeometry x="495" y="1800" width="180" height="60" as="geometry" />
                </mxCell>

                <!-- Offer Accepted Decision -->
                <mxCell id="offerAccepted" value="Offer Accepted by Client?" style="rhombus;whiteSpace=wrap;html=1;fillColor=#fff2cc;strokeColor=#d6b656;fontSize=12;fontStyle=1;" vertex="1" parent="1">
                    <mxGeometry x="510" y="1900" width="150" height="100" as="geometry" />
                </mxCell>

                <!-- Payment Received -->
                <mxCell id="paymentReceived" value="Receive Payment Notification" style="rounded=1;whiteSpace=wrap;html=1;fillColor=#dae8fc;strokeColor=#6c8ebf;fontSize=12;" vertex="1" parent="1">
                    <mxGeometry x="495" y="2050" width="180" height="60" as="geometry" />
                </mxCell>

                <!-- Process Request -->
                <mxCell id="processRequest" value="Process Booking Request" style="rounded=1;whiteSpace=wrap;html=1;fillColor=#dae8fc;strokeColor=#6c8ebf;fontSize=12;" vertex="1" parent="1">
                    <mxGeometry x="495" y="2150" width="180" height="60" as="geometry" />
                </mxCell>

                <!-- Assign Final Driver/Vehicle -->
                <mxCell id="finalAssign" value="Assign Driver to Vehicle (if not done)" style="rounded=1;whiteSpace=wrap;html=1;fillColor=#dae8fc;strokeColor=#6c8ebf;fontSize=12;" vertex="1" parent="1">
                    <mxGeometry x="475" y="2250" width="220" height="60" as="geometry" />
                </mxCell>

                <!-- End Success -->
                <mxCell id="endSuccess" value="END&#xa;(Booking Confirmed)" style="ellipse;whiteSpace=wrap;html=1;fillColor=#d5e8d4;strokeColor=#82b366;fontStyle=1;fontSize=14;" vertex="1" parent="1">
                    <mxGeometry x="525" y="2350" width="120" height="60" as="geometry" />
                </mxCell>

                <!-- End Rejected -->
                <mxCell id="endRejected" value="END&#xa;(Offer Rejected)" style="ellipse;whiteSpace=wrap;html=1;fillColor=#f8cecc;strokeColor=#b85450;fontStyle=1;fontSize=14;" vertex="1" parent="1">
                    <mxGeometry x="780" y="1970" width="120" height="60" as="geometry" />
                </mxCell>

                <!-- End Max Offers -->
                <mxCell id="endMaxOffers" value="END&#xa;(Max Offers Reached)" style="ellipse;whiteSpace=wrap;html=1;fillColor=#f8cecc;strokeColor=#b85450;fontStyle=1;fontSize=14;" vertex="1" parent="1">
                    <mxGeometry x="780" y="1570" width="130" height="60" as="geometry" />
                </mxCell>

                <!-- End Not Approved -->
                <mxCell id="endNotApproved" value="END&#xa;(Route Not Approved)" style="ellipse;whiteSpace=wrap;html=1;fillColor=#f8cecc;strokeColor=#b85450;fontStyle=1;fontSize=14;" vertex="1" parent="1">
                    <mxGeometry x="780" y="810" width="130" height="60" as="geometry" />
                </mxCell>

                <!-- Arrows -->
                <mxCell id="arrow1" style="edgeStyle=orthogonalEdgeStyle;rounded=0;orthogonalLoop=1;jettySize=auto;html=1;exitX=0.5;exitY=1;exitDx=0;exitDy=0;entryX=0.5;entryY=0;entryDx=0;entryDy=0;" edge="1" parent="1" source="start" target="signup">
                    <mxGeometry relative="1" as="geometry" />
                </mxCell>

                <mxCell id="arrow2" style="edgeStyle=orthogonalEdgeStyle;rounded=0;orthogonalLoop=1;jettySize=auto;html=1;exitX=0.5;exitY=1;exitDx=0;exitDy=0;entryX=0.5;entryY=0;entryDx=0;entryDy=0;" edge="1" parent="1" source="signup" target="emailSent">
                    <mxGeometry relative="1" as="geometry" />
                </mxCell>

                <mxCell id="arrow3" style="edgeStyle=orthogonalEdgeStyle;rounded=0;orthogonalLoop=1;jettySize=auto;html=1;exitX=0.5;exitY=1;exitDx=0;exitDy=0;entryX=0.5;entryY=0;entryDx=0;entryDy=0;" edge="1" parent="1" source="emailSent" target="emailVerified">
                    <mxGeometry relative="1" as="geometry" />
                </mxCell>

                <mxCell id="arrow4" style="edgeStyle=orthogonalEdgeStyle;rounded=0;orthogonalLoop=1;jettySize=auto;html=1;exitX=0.5;exitY=1;exitDx=0;exitDy=0;entryX=0.5;entryY=0;entryDx=0;entryDy=0;" edge="1" parent="1" source="emailVerified" target="serviceAreas">
                    <mxGeometry relative="1" as="geometry" />
                </mxCell>
                <mxCell id="arrow4label" value="YES" style="edgeLabel;html=1;align=center;verticalAlign=middle;resizable=0;points=[];fontStyle=1;" vertex="1" connectable="0" parent="arrow4">
                    <mxGeometry x="-0.2" y="1" relative="1" as="geometry">
                        <mxPoint as="offset" />
                    </mxGeometry>
                </mxCell>

                <mxCell id="arrow4b" style="edgeStyle=orthogonalEdgeStyle;rounded=0;orthogonalLoop=1;jettySize=auto;html=1;exitX=0;exitY=0.5;exitDx=0;exitDy=0;entryX=0;entryY=0.5;entryDx=0;entryDy=0;" edge="1" parent="1" source="emailVerified" target="emailSent">
                    <mxGeometry relative="1" as="geometry">
                        <Array as="points">
                            <mxPoint x="450" y="390" />
                            <mxPoint x="450" y="270" />
                        </Array>
                    </mxGeometry>
                </mxCell>
                <mxCell id="arrow4blabel" value="NO&#xa;(Resend)" style="edgeLabel;html=1;align=center;verticalAlign=middle;resizable=0;points=[];fontStyle=1;" vertex="1" connectable="0" parent="arrow4b">
                    <mxGeometry x="-0.2" y="1" relative="1" as="geometry">
                        <mxPoint x="-10" as="offset" />
                    </mxGeometry>
                </mxCell>

                <mxCell id="arrow5" style="edgeStyle=orthogonalEdgeStyle;rounded=0;orthogonalLoop=1;jettySize=auto;html=1;exitX=0.5;exitY=1;exitDx=0;exitDy=0;entryX=0.5;entryY=0;entryDx=0;entryDy=0;" edge="1" parent="1" source="serviceAreas" target="routeRequest">
                    <mxGeometry relative="1" as="geometry" />
                </mxCell>

                <mxCell id="arrow6" style="edgeStyle=orthogonalEdgeStyle;rounded=0;orthogonalLoop=1;jettySize=auto;html=1;exitX=0.5;exitY=1;exitDx=0;exitDy=0;entryX=0.5;entryY=0;entryDx=0;entryDy=0;" edge="1" parent="1" source="routeRequest" target="adminApproval">
                    <mxGeometry relative="1" as="geometry" />
                </mxCell>

                <mxCell id="arrow7" style="edgeStyle=orthogonalEdgeStyle;rounded=0;orthogonalLoop=1;jettySize=auto;html=1;exitX=0.5;exitY=1;exitDx=0;exitDy=0;entryX=0.5;entryY=0;entryDx=0;entryDy=0;" edge="1" parent="1" source="adminApproval" target="routeApproved">
                    <mxGeometry relative="1" as="geometry" />
                </mxCell>

                <mxCell id="arrow8" style="edgeStyle=orthogonalEdgeStyle;rounded=0;orthogonalLoop=1;jettySize=auto;html=1;exitX=0.5;exitY=1;exitDx=0;exitDy=0;entryX=0.5;entryY=0;entryDx=0;entryDy=0;" edge="1" parent="1" source="routeApproved" target="registerAssets">
                    <mxGeometry relative="1" as="geometry" />
                </mxCell>
                <mxCell id="arrow8label" value="YES" style="edgeLabel;html=1;align=center;verticalAlign=middle;resizable=0;points=[];fontStyle=1;" vertex="1" connectable="0" parent="arrow8">
                    <mxGeometry x="-0.2" y="1" relative="1" as="geometry">
                        <mxPoint as="offset" />
                    </mxGeometry>
                </mxCell>

                <mxCell id="arrow8b" style="edgeStyle=orthogonalEdgeStyle;rounded=0;orthogonalLoop=1;jettySize=auto;html=1;exitX=1;exitY=0.5;exitDx=0;exitDy=0;entryX=0;entryY=0.5;entryDx=0;entryDy=0;" edge="1" parent="1" source="routeApproved" target="endNotApproved">
                    <mxGeometry relative="1" as="geometry" />
                </mxCell>
                <mxCell id="arrow8blabel" value="NO" style="edgeLabel;html=1;align=center;verticalAlign=middle;resizable=0;points=[];fontStyle=1;" vertex="1" connectable="0" parent="arrow8b">
                    <mxGeometry x="-0.2" y="1" relative="1" as="geometry">
                        <mxPoint as="offset" />
                    </mxGeometry>
                </mxCell>

                <mxCell id="arrow9" style="edgeStyle=orthogonalEdgeStyle;rounded=0;orthogonalLoop=1;jettySize=auto;html=1;exitX=0.5;exitY=1;exitDx=0;exitDy=0;entryX=0.5;entryY=0;entryDx=0;entryDy=0;" edge="1" parent="1" source="registerAssets" target="assignDriver">
                    <mxGeometry relative="1" as="geometry" />
                </mxCell>

                <mxCell id="arrow10" style="edgeStyle=orthogonalEdgeStyle;rounded=0;orthogonalLoop=1;jettySize=auto;html=1;exitX=0.5;exitY=1;exitDx=0;exitDy=0;entryX=0.5;entryY=0;entryDx=0;entryDy=0;" edge="1" parent="1" source="assignDriver" target="waitBooking">
                    <mxGeometry relative="1" as="geometry" />
                </mxCell>

                <mxCell id="arrow11" style="edgeStyle=orthogonalEdgeStyle;rounded=0;orthogonalLoop=1;jettySize=auto;html=1;exitX=0.5;exitY=1;exitDx=0;exitDy=0;entryX=0.5;entryY=0;entryDx=0;entryDy=0;" edge="1" parent="1" source="waitBooking" target="bookingNotif">
                    <mxGeometry relative="1" as="geometry" />
                </mxCell>

                <mxCell id="arrow12" style="edgeStyle=orthogonalEdgeStyle;rounded=0;orthogonalLoop=1;jettySize=auto;html=1;exitX=0.5;exitY=1;exitDx=0;exitDy=0;entryX=0.5;entryY=0;entryDx=0;entryDy=0;" edge="1" parent="1" source="bookingNotif" target="viewPending">
                    <mxGeometry relative="1" as="geometry" />
                </mxCell>

                <mxCell id="arrow13" style="edgeStyle=orthogonalEdgeStyle;rounded=0;orthogonalLoop=1;jettySize=auto;html=1;exitX=0.5;exitY=1;exitDx=0;exitDy=0;entryX=0.5;entryY=0;entryDx=0;entryDy=0;" edge="1" parent="1" source="viewPending" target="createOffer">
                    <mxGeometry relative="1" as="geometry" />
                </mxCell>

                <mxCell id="arrow14" style="edgeStyle=orthogonalEdgeStyle;rounded=0;orthogonalLoop=1;jettySize=auto;html=1;exitX=0.5;exitY=1;exitDx=0;exitDy=0;entryX=0.5;entryY=0;entryDx=0;entryDy=0;" edge="1" parent="1" source="createOffer" target="offerCount">
                    <mxGeometry relative="1" as="geometry" />
                </mxCell>

                <mxCell id="arrow15" style="edgeStyle=orthogonalEdgeStyle;rounded=0;orthogonalLoop=1;jettySize=auto;html=1;exitX=0.5;exitY=1;exitDx=0;exitDy=0;entryX=0.5;entryY=0;entryDx=0;entryDy=0;" edge="1" parent="1" source="offerCount" target="submitOffer">
                    <mxGeometry relative="1" as="geometry" />
                </mxCell>
                <mxCell id="arrow15label" value="YES" style="edgeLabel;html=1;align=center;verticalAlign=middle;resizable=0;points=[];fontStyle=1;" vertex="1" connectable="0" parent="arrow15">
                    <mxGeometry x="-0.2" y="1" relative="1" as="geometry">
                        <mxPoint as="offset" />
                    </mxGeometry>
                </mxCell>

                <mxCell id="arrow15b" style="edgeStyle=orthogonalEdgeStyle;rounded=0;orthogonalLoop=1;jettySize=auto;html=1;exitX=1;exitY=0.5;exitDx=0;exitDy=0;entryX=0;entryY=0.5;entryDx=0;entryDy=0;" edge="1" parent="1" source="offerCount" target="endMaxOffers">
                    <mxGeometry relative="1" as="geometry" />
                </mxCell>
                <mxCell id="arrow15blabel" value="NO" style="edgeLabel;html=1;align=center;verticalAlign=middle;resizable=0;points=[];fontStyle=1;" vertex="1" connectable="0" parent="arrow15b">
                    <mxGeometry x="-0.2" y="1" relative="1" as="geometry">
                        <mxPoint as="offset" />
                    </mxGeometry>
                </mxCell>

                <mxCell id="arrow16" style="edgeStyle=orthogonalEdgeStyle;rounded=0;orthogonalLoop=1;jettySize=auto;html=1;exitX=0.5;exitY=1;exitDx=0;exitDy=0;entryX=0.5;entryY=0;entryDx=0;entryDy=0;" edge="1" parent="1" source="submitOffer" target="waitResponse">
                    <mxGeometry relative="1" as="geometry" />
                </mxCell>

                <mxCell id="arrow17" style="edgeStyle=orthogonalEdgeStyle;rounded=0;orthogonalLoop=1;jettySize=auto;html=1;exitX=0.5;exitY=1;exitDx=0;exitDy=0;entryX=0.5;entryY=0;entryDx=0;entryDy=0;" edge="1" parent="1" source="waitResponse" target="offerAccepted">
                    <mxGeometry relative="1" as="geometry" />
                </mxCell>

                <mxCell id="arrow18" style="edgeStyle=orthogonalEdgeStyle;rounded=0;orthogonalLoop=1;jettySize=auto;html=1;exitX=0.5;exitY=1;exitDx=0;exitDy=0;entryX=0.5;entryY=0;entryDx=0;entryDy=0;" edge="1" parent="1" source="offerAccepted" target="paymentReceived">
                    <mxGeometry relative="1" as="geometry" />
                </mxCell>
                <mxCell id="arrow18label" value="YES" style="edgeLabel;html=1;align=center;verticalAlign=middle;resizable=0;points=[];fontStyle=1;" vertex="1" connectable="0" parent="arrow18">
                    <mxGeometry x="-0.2" y="1" relative="1" as="geometry">
                        <mxPoint as="offset" />
                    </mxGeometry>
                </mxCell>

                <mxCell id="arrow18b" style="edgeStyle=orthogonalEdgeStyle;rounded=0;orthogonalLoop=1;jettySize=auto;html=1;exitX=1;exitY=0.5;exitDx=0;exitDy=0;entryX=0;entryY=0.5;entryDx=0;entryDy=0;" edge="1" parent="1" source="offerAccepted" target="endRejected">
                    <mxGeometry relative="1" as="geometry" />
                </mxCell>
                <mxCell id="arrow18blabel" value="NO" style="edgeLabel;html=1;align=center;verticalAlign=middle;resizable=0;points=[];fontStyle=1;" vertex="1" connectable="0" parent="arrow18b">
                    <mxGeometry x="-0.2" y="1" relative="1" as="geometry">
                        <mxPoint as="offset" />
                    </mxGeometry>
                </mxCell>

                <mxCell id="arrow19" style="edgeStyle=orthogonalEdgeStyle;rounded=0;orthogonalLoop=1;jettySize=auto;html=1;exitX=0.5;exitY=1;exitDx=0;exitDy=0;entryX=0.5;entryY=0;entryDx=0;entryDy=0;" edge="1" parent="1" source="paymentReceived" target="processRequest">
                    <mxGeometry relative="1" as="geometry" />
                </mxCell>

                <mxCell id="arrow20" style="edgeStyle=orthogonalEdgeStyle;rounded=0;orthogonalLoop=1;jettySize=auto;html=1;exitX=0.5;exitY=1;exitDx=0;exitDy=0;entryX=0.5;entryY=0;entryDx=0;entryDy=0;" edge="1" parent="1" source="processRequest" target="finalAssign">
                    <mxGeometry relative="1" as="geometry" />
                </mxCell>

                <mxCell id="arrow21" style="edgeStyle=orthogonalEdgeStyle;rounded=0;orthogonalLoop=1;jettySize=auto;html=1;exitX=0.5;exitY=1;exitDx=0;exitDy=0;entryX=0.5;entryY=0;entryDx=0;entryDy=0;" edge="1" parent="1" source="finalAssign" target="endSuccess">
                    <mxGeometry relative="1" as="geometry" />
                </mxCell>

            </root>
        </mxGraphModel>
    </diagram>
</mxfile>